up_pyperplan/__init__.py
up_pyperplan/engine.py
up_pyperplan/grounder.py
up_pyperplan-1.0.0.dist-info/LICENSE
up_pyperplan-1.0.0.dist-info/METADATA
up_pyperplan-1.0.0.dist-info/WHEEL
up_pyperplan-1.0.0.dist-info/top_level.txt
up_pyperplan-1.0.0.dist-info/RECORD
