Metadata-Version: 2.1
Name: up-pyperplan
Version: 1.0.0
Summary: up_pyperplan
Home-page: https://www.aiplan4eu-project.eu
Author: AIPlan4EU Organization
Author-email: aiplan4eu@fbk.eu
License: APACHE
Platform: UNKNOWN
Requires-Python: >=3.7
Requires-Dist: pyperplan (==2.1)
